{
    "5JVz47MsL": {
        "unique_id": "5JVz47MsL",
        "posted_date": "2024-12-19 09:13:32",
        "updated_date": "2024-12-19 09:13:32"
    },
    "n7UeYNq9m": {
        "unique_id": "n7UeYNq9m",
        "posted_date": "2024-12-19 09:17:41",
        "updated_date": "2024-12-19 09:17:41"
    },
    "BLO5WCnU2": {
        "unique_id": "BLO5WCnU2",
        "posted_date": "2024-12-19 09:21:48",
        "updated_date": "2024-12-22 04:54:54"
    },
    "6clKGk0ds": {
        "unique_id": "6clKGk0ds",
        "posted_date": "2024-12-19 09:23:39",
        "updated_date": "2024-12-19 09:23:39"
    },
    "umCdy8Yb2": {
        "unique_id": "umCdy8Yb2",
        "posted_date": "2024-12-19 09:24:03",
        "updated_date": "2024-12-19 09:24:03"
    },
    "f1IoEPxTX": {
        "unique_id": "f1IoEPxTX",
        "posted_date": "2024-12-19 09:35:08",
        "updated_date": "2024-12-19 09:35:08"
    },
    "8t2jpDsAm": {
        "unique_id": "8t2jpDsAm",
        "posted_date": "2024-12-19 09:35:54",
        "updated_date": "2024-12-19 09:35:54"
    },
    "6u8YjfwlS": {
        "unique_id": "6u8YjfwlS",
        "posted_date": "2024-12-29 10:56:24",
        "updated_date": "2024-12-29 10:56:24"
    },
    "WqQDc4M1A": {
        "unique_id": "WqQDc4M1A",
        "posted_date": "2024-12-29 11:28:56",
        "updated_date": "2024-12-29 11:31:05",
        "status": "private"
    },
    "ZSCouFhXk": {
        "unique_id": "ZSCouFhXk",
        "posted_date": "2024-12-29 11:46:26",
        "updated_date": "2024-12-29 11:46:26"
    },
    "fnHqa8moA": {
        "unique_id": "fnHqa8moA",
        "posted_date": "2024-12-29 11:48:56",
        "updated_date": "2024-12-29 11:48:56"
    },
    "kJ1gBb72X": {
        "unique_id": "kJ1gBb72X",
        "posted_date": "2024-12-29 11:49:17",
        "updated_date": "2024-12-29 11:49:17"
    },
    "dzyRTpFti": {
        "unique_id": "dzyRTpFti",
        "posted_date": "2024-12-29 12:24:00",
        "updated_date": "2024-12-29 12:24:00"
    },
    "HiEQ5S2Pt": {
        "unique_id": "HiEQ5S2Pt",
        "posted_date": "2024-12-29 12:24:37",
        "updated_date": "2024-12-29 12:24:37"
    }
}